iclik/inform_crit.py
iclik/matrices.py
iclik-0.1.10a0.dist-info/LICENSE
iclik-0.1.10a0.dist-info/METADATA
iclik-0.1.10a0.dist-info/WHEEL
iclik-0.1.10a0.dist-info/top_level.txt
iclik-0.1.10a0.dist-info/RECORD
