Metadata-Version: 2.1
Name: iclik
Version: 0.1.10a0
Summary: Information criteria for composite likelihood models
License-File: LICENSE
Requires-Dist: numdifftools
Requires-Dist: numpy
Requires-Dist: scipy
